{"status": null, "abilities": {"intro": {"has": false, "can": false}}, "crunchbase_url": null, "video_url": null, "company_url": "http://Coming Soon", "company_type": [], "locations": [{"angellist_url": "https://angel.co/san-francisco", "display_name": "San Francisco", "id": 1692, "name": "san francisco", "tag_type": "LocationTag"}], "quality": 3, "id": 883653, "angellist_url": "https://angel.co/closesync", "screenshots": [], "follower_count": 2, "hidden": false, "logo_url": "https://d1qb2nb5cznatu.cloudfront.net/startups/i/883653-ad56002b16e8e60b60fc64daf8a96d93-medium_jpg.jpg?buster=1445388227", "markets": [{"angellist_url": "https://angel.co/social-media", "display_name": "Social Media", "id": 6, "name": "social media", "tag_type": "MarketTag"}, {"angellist_url": "https://angel.co/mobile-application-3", "display_name": "Mobile Application", "id": 153266, "name": "mobile application", "tag_type": "MarketTag"}], "community_profile": false, "product_desc": "A mobile application on the IOS platform, that will help to re-define the way people connect.", "twitter_url": null, "high_concept": "A revolutionary mobile social media network", "facebook_url": null, "updated_at": "2015-10-21T00:44:04Z", "thumb_url": "https://d1qb2nb5cznatu.cloudfront.net/startups/i/883653-ad56002b16e8e60b60fc64daf8a96d93-thumb_jpg.jpg?buster=1445388227", "company_size": "1-10", "name": "CloseSync", "created_at": "2015-10-21T00:44:04Z", "linkedin_url": null, "blog_url": null}