{"status": null, "abilities": {"intro": {"has": false, "can": false}}, "crunchbase_url": null, "video_url": null, "company_url": "", "company_type": [{"angellist_url": "https://angel.co/product-development-4", "display_name": "Product Development", "id": 149548, "name": "Product Development", "tag_type": "CompanyTypeTag"}], "locations": [{"angellist_url": "https://angel.co/los-angeles", "display_name": "Los Angeles", "id": 1653, "name": "los angeles", "tag_type": "LocationTag"}], "quality": 3, "id": 882000, "angellist_url": "https://angel.co/the-renegade-firm", "screenshots": [], "follower_count": 1, "hidden": false, "logo_url": "https://d1qb2nb5cznatu.cloudfront.net/startups/i/882000-e097b54e1fe7c0bee32557de2f81851b-medium_jpg.jpg?buster=1445296746", "markets": [{"angellist_url": "https://angel.co/mobile-2", "display_name": "Mobile", "id": 3, "name": "mobile", "tag_type": "MarketTag"}, {"angellist_url": "https://angel.co/web-design", "display_name": "Web Design", "id": 332, "name": "web design", "tag_type": "MarketTag"}, {"angellist_url": "https://angel.co/product-development-services", "display_name": "Product Development Services", "id": 411, "name": "product development services", "tag_type": "MarketTag"}, {"angellist_url": "https://angel.co/user-experience-design", "display_name": "User Experience Design", "id": 11826, "name": "user experience design", "tag_type": "MarketTag"}], "community_profile": false, "product_desc": null, "twitter_url": "", "high_concept": "Product development with a foundation built on empathy, mindfulness, and context.", "facebook_url": "", "updated_at": "2015-10-19T23:19:11Z", "thumb_url": "https://d1qb2nb5cznatu.cloudfront.net/startups/i/882000-e097b54e1fe7c0bee32557de2f81851b-thumb_jpg.jpg?buster=1445296746", "company_size": "1-10", "name": "The Renegade Firm", "created_at": "2015-10-19T23:12:13Z", "linkedin_url": "", "blog_url": ""}